artd_urls/__init__.py
artd_urls/admin.py
artd_urls/apps.py
artd_urls/models.py
artd_urls/signals.py
artd_urls/tests.py
artd_urls/views.py
artd_urls/management/__init__.py
artd_urls/management/commands/__init__.py
artd_urls/management/commands/refresh_all_urls.py
artd_urls/migrations/0001_initial.py
artd_urls/migrations/0002_alter_url_partner_alter_urlconfiguration_partner.py
artd_urls/migrations/0003_rename_decorator_url_decorators.py
artd_urls/migrations/0004_alter_url_partner_alter_urlconfiguration_partner.py
artd_urls/migrations/0005_alter_url_partner_alter_urlconfiguration_partner.py
artd_urls/migrations/__init__.py
artd_urls/utils/__init__.py
artd_urls/utils/urls_util.py
urls/__init__.py
urls/asgi.py
urls/settings.py
urls/urls.py
urls/wsgi.py
artd_url-1.0.5.dist-info/LICENSE
artd_url-1.0.5.dist-info/METADATA
artd_url-1.0.5.dist-info/WHEEL
artd_url-1.0.5.dist-info/top_level.txt
artd_url-1.0.5.dist-info/RECORD
